odoo8_addon_hr_holidays_legal_leave-8.0.1.0.0.99.dev20-py2.7-nspkg.pth
odoo8_addon_hr_holidays_legal_leave-8.0.1.0.0.99.dev20.dist-info/DESCRIPTION.rst
odoo8_addon_hr_holidays_legal_leave-8.0.1.0.0.99.dev20.dist-info/METADATA
odoo8_addon_hr_holidays_legal_leave-8.0.1.0.0.99.dev20.dist-info/RECORD
odoo8_addon_hr_holidays_legal_leave-8.0.1.0.0.99.dev20.dist-info/WHEEL
odoo8_addon_hr_holidays_legal_leave-8.0.1.0.0.99.dev20.dist-info/metadata.json
odoo8_addon_hr_holidays_legal_leave-8.0.1.0.0.99.dev20.dist-info/namespace_packages.txt
odoo8_addon_hr_holidays_legal_leave-8.0.1.0.0.99.dev20.dist-info/top_level.txt
odoo_addons/hr_holidays_legal_leave/README.rst
odoo_addons/hr_holidays_legal_leave/__init__.py
odoo_addons/hr_holidays_legal_leave/__openerp__.py
odoo_addons/hr_holidays_legal_leave/i18n/am.po
odoo_addons/hr_holidays_legal_leave/i18n/ar.po
odoo_addons/hr_holidays_legal_leave/i18n/ca.po
odoo_addons/hr_holidays_legal_leave/i18n/da.po
odoo_addons/hr_holidays_legal_leave/i18n/de.po
odoo_addons/hr_holidays_legal_leave/i18n/el_GR.po
odoo_addons/hr_holidays_legal_leave/i18n/es.po
odoo_addons/hr_holidays_legal_leave/i18n/es_ES.po
odoo_addons/hr_holidays_legal_leave/i18n/es_MX.po
odoo_addons/hr_holidays_legal_leave/i18n/fi.po
odoo_addons/hr_holidays_legal_leave/i18n/fr.po
odoo_addons/hr_holidays_legal_leave/i18n/fr_CA.po
odoo_addons/hr_holidays_legal_leave/i18n/fr_FR.po
odoo_addons/hr_holidays_legal_leave/i18n/hr.po
odoo_addons/hr_holidays_legal_leave/i18n/hr_HR.po
odoo_addons/hr_holidays_legal_leave/i18n/hr_holidays_legal_leave.pot
odoo_addons/hr_holidays_legal_leave/i18n/it.po
odoo_addons/hr_holidays_legal_leave/i18n/nb.po
odoo_addons/hr_holidays_legal_leave/i18n/nb_NO.po
odoo_addons/hr_holidays_legal_leave/i18n/nl.po
odoo_addons/hr_holidays_legal_leave/i18n/nl_BE.po
odoo_addons/hr_holidays_legal_leave/i18n/nl_NL.po
odoo_addons/hr_holidays_legal_leave/i18n/pt_BR.po
odoo_addons/hr_holidays_legal_leave/i18n/ro.po
odoo_addons/hr_holidays_legal_leave/i18n/sk.po
odoo_addons/hr_holidays_legal_leave/i18n/sl.po
odoo_addons/hr_holidays_legal_leave/i18n/tr.po
odoo_addons/hr_holidays_legal_leave/i18n/zh_CN.po
odoo_addons/hr_holidays_legal_leave/models/__init__.py
odoo_addons/hr_holidays_legal_leave/models/hr_employee.py
odoo_addons/hr_holidays_legal_leave/models/res_company.py
odoo_addons/hr_holidays_legal_leave/models/res_config.py
odoo_addons/hr_holidays_legal_leave/static/description/icon.png
odoo_addons/hr_holidays_legal_leave/tests/__init__.py
