Metadata-Version: 2.0
Name: odoo8-addon-hr-holidays-legal-leave
Version: 8.0.1.0.0.99.dev20
Summary: Allows the definition of legal/annual leave
Home-page: http://idtlabs.sl
Author: iDT LABS, Odoo Community Association (OCA)
Author-email: support@odoo-community.org
License: AGPL-3
Platform: UNKNOWN
Classifier: Programming Language :: Python
Classifier: Framework :: Odoo
Classifier: License :: OSI Approved :: GNU Affero General Public License v3
Requires-Python: ~=2.7
Requires-Dist: odoo (<9.0a,>=8.0a)
